neutron-transport-fpga/math/cordicc/cordicstagec.vhd
-- Calcola lo step unitario dell'Algoritmo CORDIC Trigonometrico in Modalità Rotazionale
-- per il calcolo delle funzioni sin e cos
library ieee;
use ieee.std_logic_1164.all;
use ieee.numeric_std.all;
use work.config.all;
use work.configcordic.all;
use work.configcordicc.all;


entity cordicstagec is 
    generic (
        iter : integer := 0
    );
    port (
        clk      : in  std_logic;
        rst      : in  std_logic;

        statein  : in  cordicstate_t;
        alpha    : in  signed(m_blocksize * m_blocks - 1 downto 0); -- atanlut value
        
        stateout : out cordicstate_t
    );
end entity cordicstagec;


architecture rtl of cordicstagec is 

begin 
    compute : process (clk, rst) begin 
        if rst = '1' then 
            stateout <= ((others => '0'), (others => '0'), (others => '0'));
            
        elsif rising_edge(clk) then 
            -- Modalità rotazione: riduciamo Z a 0
            if statein.z < (statein.z'range => '0') then 
                -- Z è negativo, 
                -- x' = x + (y >> iter)
                -- y' = y - (x >> iter)
                -- z' = z + alpha
                stateout.x <= statein.x + shift_right(statein.y, iter);
                stateout.y <= statein.y - shift_right(statein.x, iter);
                stateout.z <= statein.z + alpha;
            else
                -- Z è positivo,
                -- x' = x - (y >> iter)
                -- y' = y + (x >> iter)
                -- z' = z - alpha 
                stateout.x <= statein.x - shift_right(statein.y, iter);
                stateout.y <= statein.y + shift_right(statein.x, iter);
                stateout.z <= statein.z - alpha;
            end if;
        end if;
    end process compute;
end architecture rtl;

neutron-transport-fpga/math/cordicc/cordicc.vhd
library ieee;
use ieee.std_logic_1164.all;
use ieee.numeric_std.all;
use work.config.all;
use work.configcordic.all;
use work.configcordicc.all;


entity cordicc is 
    port (
        clk      : in  std_logic;
        rst      : in  std_logic;

        statein  : in  cordicstate_t;
        stateout : out cordicstate_t
    );
end entity cordicc;


architecture rtl of cordicc is 
    type cordiccpipe_t is array (0 to m_maxiterc) of cordicstate_t;
    signal stages : cordiccpipe_t := (others => ((others => '0'), (others => '0'), (others => '0'))); -- combinatorial output

begin   
    -- combinatorial assignment of first stage
    stages(0) <= statein;

    -- compute intermediate stages
    genstages: for i in 0 to m_maxiterc - 1 generate 
        cstage : entity work.cordicstagec(rtl)
            generic map ( iter => i )
            port map (
                clk      => clk,
                rst      => rst,

                statein  => stages(i),
                alpha    => atanlut(i),
                stateout => stages(i + 1)
            );
    end generate genstages;

    -- Output Connection
    stateout <= stages(stages'high);

end architecture rtl;

neutron-transport-fpga/math/cordicc/reduceangle.vhd
library ieee;
use ieee.std_logic_1164.all;
use ieee.numeric_std.all;
use work.config.all;
use work.configcordic.all;
use work.configcordicc.all;

-- Riduce l'angolo alpha nel range [-pi/2, pi/2] e calcola il flip del coseno
entity reduceangle is
	port (
		clk    : in  std_logic;
		rst    : in  std_logic;
        
		alpha  : in  signed(m_blocksize * m_blocks - 1 downto 0); -- angolo input Q16.48
		alphar : out signed(m_blocksize * m_blocks - 1 downto 0); -- angolo ridotto Q16.48
		flip   : out std_logic            -- flip segno coseno, output flag
	);
end entity reduceangle;


architecture rtl of reduceangle is
begin
	process(clk, rst)
	begin
		if rst = '1' then
			alphar <= (others => '0');
            flip   <= '0';

		elsif rising_edge(clk) then
			if ((alpha > m_pi_2) and (alpha < m_3pi_2)) then
                -- se alpha nel secondo o terzo quadrante, riduci alpha
                -- flip angle
				alphar <= m_pi - alpha;
				flip   <= '1'; -- flip segno coseno
			else 
                -- alpha nel primo o quarto quadrante
                -- no flip
                alphar <= alpha;
                flip   <= '0';
            end if;
		end if;
	end process;
end architecture rtl;

neutron-transport-fpga/math/cordicc/sincos.vhd

library ieee;
use ieee.std_logic_1164.all;
use ieee.numeric_std.all;
use work.config.all;
use work.configcordic.all;
use work.configcordicc.all;


-- latenza massima: m_maxiterc + 1 cicli (m_maxiterc per le iterazioni + 1 per la riduzione angolo)
entity sincos is
	port (
		clk   : in  std_logic;
		rst   : in  std_logic;

		alpha : in  signed(m_blocksize * m_blocks - 1 downto 0); -- angolo input Q16.48
		s     : out signed(m_blocksize * m_blocks - 1 downto 0); -- sin output Q16.48
		c     : out signed(m_blocksize * m_blocks - 1 downto 0)  -- cos output Q16.48
	);
end entity sincos;


architecture rtl of sincos is
    signal alphar    : signed(m_blocksize * m_blocks - 1 downto 0);
    signal flip      : std_logic;
    signal stateout  : cordicstate_t;
    signal statein_sig : cordicstate_t; -- Intermediate signal for state input

begin
	-- Riduzione angolo e flip segno coseno
	reduce : entity work.reduceangle(rtl)
		port map (
			clk    => clk,
			rst    => rst,

			alpha  => alpha,
			alphar => alphar,
			flip   => flip
		);

	-- Build state input signal
	statein_sig <= (kcinv, (others => '0'), alphar);

	-- CORDIC trigonometrico
	cordicc : entity work.cordicc(rtl)
		port map (
			clk   => clk,
			rst   => rst,

			statein => statein_sig, -- x = 1/K, y = 0, z = alphar
	           stateout => stateout
		);

	-- Output: applica flip segno coseno
	s <= stateout.y;
    c <= stateout.x when flip = '0' else -stateout.x;

end architecture rtl;

neutron-transport-fpga/test/testcordic/tb_sincos.vhd
library ieee;
use ieee.std_logic_1164.all;
use ieee.numeric_std.all;
use work.config.all;
use work.configcordic.all;
use work.configcordicc.all;

entity tb_sincos is
end entity tb_sincos;

architecture test of tb_sincos is
    constant period : time := 10 ns;

	signal clk   : std_logic := '1';
	signal rst   : std_logic := '1';
	signal alpha : signed(m_blocksize * m_blocks - 1 downto 0) := (others => '0');
	signal s     : signed(m_blocksize * m_blocks - 1 downto 0);
	signal c     : signed(m_blocksize * m_blocks - 1 downto 0);

	-- Angoli noti (0, pi/4, pi/2, pi, 3pi/2, 2pi)
	type angle_arr is array(0 to 5) of signed(m_blocksize * m_blocks - 1 downto 0);
	constant zero    : signed(m_blocksize * m_blocks - 1 downto 0) := (others => '0');
	constant pi      : signed(m_blocksize * m_blocks - 1 downto 0) := x"0003_243F6A8885A3";
	constant pi_2    : signed(m_blocksize * m_blocks - 1 downto 0) := x"0001_921FB54442D1";
	constant pi_4    : signed(m_blocksize * m_blocks - 1 downto 0) := x"0000_C90FDAA22168";
	constant t3pi_2  : signed(m_blocksize * m_blocks - 1 downto 0) := x"0004_B65F29CCD067";
	constant t2pi    : signed(m_blocksize * m_blocks - 1 downto 0) := x"0006_487ED5110B46";
	constant known_angles : angle_arr := (zero, pi_4, pi_2, pi, t3pi_2, t2pi);

	-- Semplice LFSR per random
	signal lfsr : std_logic_vector(31 downto 0) := x"1A2B3C4D";

begin
	
	dut : entity work.sincos(rtl)
		port map (
			clk   => clk,
			rst   => rst,
			
            alpha => alpha,
			s     => s,
			c     => c
		);


    clock : process begin 
        clk <= '0';
        wait for period / 2;

        clk <= not clk;
        wait for period / 2;
    end process clock;

	stimulus : process begin
        rst <= '1';
        wait until rising_edge(clk);

        rst <= '0';
        wait until rising_edge(clk);


        -- 30°
        alpha <= X"0000860A91C16B9B";
        wait until rising_edge(clk);

        -- 45°
        alpha <= X"0000C90FDAA22169";
        wait until rising_edge(clk);
        
        -- 60°
        alpha <= X"00010C152382D736";
        wait until rising_edge(clk);
        
        -- 90°
        alpha <= X"0001921FB54442D2";
        wait until rising_edge(clk);
        
        -- 120°
        alpha <= X"0002182A4705AE6D";
        wait until rising_edge(clk);
        
        -- 150° 
        alpha <= X"00029E34D8C71A08";
        wait until rising_edge(clk);
        
        -- 180°    
        alpha <= X"0003243F6A8885A3";
        wait until rising_edge(clk);
        wait for 50 * period; -- latency + 2 periodi di margine

        wait; -- fine della simulazione
    end process stimulus;

end architecture test;

neutron-transport-fpga/tb_sincos.vcd
$date
  Thu Feb 26 14:18:02 2026
$end
$version
  GHDL v0
$end
$timescale
  1 fs
$end
$scope module standard $end
$upscope $end
$scope module textio $end
$upscope $end
$scope module std_logic_1164 $end
$upscope $end
$scope module numeric_std $end
$upscope $end
$scope module config $end
$upscope $end
$scope module configcordic $end
$upscope $end
$scope module configcordicc $end
$upscope $end
$scope module tb_sincos $end
$var reg 1 ! clk $end
$var reg 1 " rst $end
$var reg 64 # alpha[63:0] $end
$var reg 64 $ s[63:0] $end
$var reg 64 % c[63:0] $end
$var reg 32 & lfsr[31:0] $end
$scope module dut $end
$var reg 1 ' clk $end
$var reg 1 ( rst $end
$var reg 64 ) alpha[63:0] $end
$var reg 64 * s[63:0] $end
$var reg 64 + c[63:0] $end
$var reg 64 , alphar[63:0] $end
$var reg 1 - flip $end
$comment stateout is not handled $end
$comment statein_sig is not handled $end
$scope module reduce $end
$var reg 1 . clk $end
$var reg 1 / rst $end
$var reg 64 0 alpha[63:0] $end
$var reg 64 1 alphar[63:0] $end
$var reg 1 2 flip $end
$upscope $end
$scope module cordicc $end
$var reg 1 3 clk $end
$var reg 1 4 rst $end
$comment statein is not handled $end
$comment stateout is not handled $end
$comment stages is not handled $end
$scope module genstages(0) $end
$scope module cstage $end
$var reg 1 5 clk $end
$var reg 1 6 rst $end
$comment statein is not handled $end
$var reg 64 7 alpha[63:0] $end
$comment stateout is not handled $end
$upscope $end
$upscope $end
$scope module genstages(1) $end
$scope module cstage $end
$var reg 1 8 clk $end
$var reg 1 9 rst $end
$comment statein is not handled $end
$var reg 64 : alpha[63:0] $end
$comment stateout is not handled $end
$upscope $end
$upscope $end
$scope module genstages(2) $end
$scope module cstage $end
$var reg 1 ; clk $end
$var reg 1 < rst $end
$comment statein is not handled $end
$var reg 64 = alpha[63:0] $end
$comment stateout is not handled $end
$upscope $end
$upscope $end
$scope module genstages(3) $end
$scope module cstage $end
$var reg 1 > clk $end
$var reg 1 ? rst $end
$comment statein is not handled $end
$var reg 64 @ alpha[63:0] $end
$comment stateout is not handled $end
$upscope $end
$upscope $end
$scope module genstages(4) $end
$scope module cstage $end
$var reg 1 A clk $end
$var reg 1 B rst $end
$comment statein is not handled $end
$var reg 64 C alpha[63:0] $end
$comment stateout is not handled $end
$upscope $end
$upscope $end
$scope module genstages(5) $end
$scope module cstage $end
$var reg 1 D clk $end
$var reg 1 E rst $end
$comment statein is not handled $end
$var reg 64 F alpha[63:0] $end
$comment stateout is not handled $end
$upscope $end
$upscope $end
$scope module genstages(6) $end
$scope module cstage $end
$var reg 1 G clk $end
$var reg 1 H rst $end
$comment statein is not handled $end
$var reg 64 I alpha[63:0] $end
$comment stateout is not handled $end
$upscope $end
$upscope $end
$scope module genstages(7) $end
$scope module cstage $end
$var reg 1 J clk $end
$var reg 1 K rst $end
$comment statein is not handled $end
$var reg 64 L alpha[63:0] $end
$comment stateout is not handled $end
$upscope $end
$upscope $end
$scope module genstages(8) $end
$scope module cstage $end
$var reg 1 M clk $end
$var reg 1 N rst $end
$comment statein is not handled $end
$var reg 64 O alpha[63:0] $end
$comment stateout is not handled $end
$upscope $end
$upscope $end
$scope module genstages(9) $end
$scope module cstage $end
$var reg 1 P clk $end
$var reg 1 Q rst $end
$comment statein is not handled $end
$var reg 64 R alpha[63:0] $end
$comment stateout is not handled $end
$upscope $end
$upscope $end
$scope module genstages(10) $end
$scope module cstage $end
$var reg 1 S clk $end
$var reg 1 T rst $end
$comment statein is not handled $end
$var reg 64 U alpha[63:0] $end
$comment stateout is not handled $end
$upscope $end
$upscope $end
$scope module genstages(11) $end
$scope module cstage $end
$var reg 1 V clk $end
$var reg 1 W rst $end
$comment statein is not handled $end
$var reg 64 X alpha[63:0] $end
$comment stateout is not handled $end
$upscope $end
$upscope $end
$scope module genstages(12) $end
$scope module cstage $end
$var reg 1 Y clk $end
$var reg 1 Z rst $end
$comment statein is not handled $end
$var reg 64 [ alpha[63:0] $end
$comment stateout is not handled $end
$upscope $end
$upscope $end
$scope module genstages(13) $end
$scope module cstage $end
$var reg 1 \ clk $end
$var reg 1 ] rst $end
$comment statein is not handled $end
$var reg 64 ^ alpha[63:0] $end
$comment stateout is not handled $end
$upscope $end
$upscope $end
$scope module genstages(14) $end
$scope module cstage $end
$var reg 1 _ clk $end
$var reg 1 ` rst $end
$comment statein is not handled $end
$var reg 64 a alpha[63:0] $end
$comment stateout is not handled $end
$upscope $end
$upscope $end
$scope module genstages(15) $end
$scope module cstage $end
$var reg 1 b clk $end
$var reg 1 c rst $end
$comment statein is not handled $end
$var reg 64 d alpha[63:0] $end
$comment stateout is not handled $end
$upscope $end
$upscope $end
$scope module genstages(16) $end
$scope module cstage $end
$var reg 1 e clk $end
$var reg 1 f rst $end
$comment statein is not handled $end
$var reg 64 g alpha[63:0] $end
$comment stateout is not handled $end
$upscope $end
$upscope $end
$scope module genstages(17) $end
$scope module cstage $end
$var reg 1 h clk $end
$var reg 1 i rst $end
$comment statein is not handled $end
$var reg 64 j alpha[63:0] $end
$comment stateout is not handled $end
$upscope $end
$upscope $end
$scope module genstages(18) $end
$scope module cstage $end
$var reg 1 k clk $end
$var reg 1 l rst $end
$comment statein is not handled $end
$var reg 64 m alpha[63:0] $end
$comment stateout is not handled $end
$upscope $end
$upscope $end
$scope module genstages(19) $end
$scope module cstage $end
$var reg 1 n clk $end
$var reg 1 o rst $end
$comment statein is not handled $end
$var reg 64 p alpha[63:0] $end
$comment stateout is not handled $end
$upscope $end
$upscope $end
$scope module genstages(20) $end
$scope module cstage $end
$var reg 1 q clk $end
$var reg 1 r rst $end
$comment statein is not handled $end
$var reg 64 s alpha[63:0] $end
$comment stateout is not handled $end
$upscope $end
$upscope $end
$scope module genstages(21) $end
$scope module cstage $end
$var reg 1 t clk $end
$var reg 1 u rst $end
$comment statein is not handled $end
$var reg 64 v alpha[63:0] $end
$comment stateout is not handled $end
$upscope $end
$upscope $end
$scope module genstages(22) $end
$scope module cstage $end
$var reg 1 w clk $end
$var reg 1 x rst $end
$comment statein is not handled $end
$var reg 64 y alpha[63:0] $end
$comment stateout is not handled $end
$upscope $end
$upscope $end
$scope module genstages(23) $end
$scope module cstage $end
$var reg 1 z clk $end
$var reg 1 { rst $end
$comment statein is not handled $end
$var reg 64 | alpha[63:0] $end
$comment stateout is not handled $end
$upscope $end
$upscope $end
$scope module genstages(24) $end
$scope module cstage $end
$var reg 1 } clk $end
$var reg 1 !" rst $end
$comment statein is not handled $end
$var reg 64 "" alpha[63:0] $end
$comment stateout is not handled $end
$upscope $end
$upscope $end
$scope module genstages(25) $end
$scope module cstage $end
$var reg 1 #" clk $end
$var reg 1 $" rst $end
$comment statein is not handled $end
$var reg 64 %" alpha[63:0] $end
$comment stateout is not handled $end
$upscope $end
$upscope $end
$scope module genstages(26) $end
$scope module cstage $end
$var reg 1 &" clk $end
$var reg 1 '" rst $end
$comment statein is not handled $end
$var reg 64 (" alpha[63:0] $end
$comment stateout is not handled $end
$upscope $end
$upscope $end
$scope module genstages(27) $end
$scope module cstage $end
$var reg 1 )" clk $end
$var reg 1 *" rst $end
$comment statein is not handled $end
$var reg 64 +" alpha[63:0] $end
$comment stateout is not handled $end
$upscope $end
$upscope $end
$scope module genstages(28) $end
$scope module cstage $end
$var reg 1 ," clk $end
$var reg 1 -" rst $end
$comment statein is not handled $end
$var reg 64 ." alpha[63:0] $end
$comment stateout is not handled $end
$upscope $end
$upscope $end
$scope module genstages(29) $end
$scope module cstage $end
$var reg 1 /" clk $end
$var reg 1 0" rst $end
$comment statein is not handled $end
$var reg 64 1" alpha[63:0] $end
$comment stateout is not handled $end
$upscope $end
$upscope $end
$scope module genstages(30) $end
$scope module cstage $end
$var reg 1 2" clk $end
$var reg 1 3" rst $end
$comment statein is not handled $end
$var reg 64 4" alpha[63:0] $end
$comment stateout is not handled $end
$upscope $end
$upscope $end
$scope module genstages(31) $end
$scope module cstage $end
$var reg 1 5" clk $end
$var reg 1 6" rst $end
$comment statein is not handled $end
$var reg 64 7" alpha[63:0] $end
$comment stateout is not handled $end
$upscope $end
$upscope $end
$scope module genstages(32) $end
$scope module cstage $end
$var reg 1 8" clk $end
$var reg 1 9" rst $end
$comment statein is not handled $end
$var reg 64 :" alpha[63:0] $end
$comment stateout is not handled $end
$upscope $end
$upscope $end
$scope module genstages(33) $end
$scope module cstage $end
$var reg 1 ;" clk $end
$var reg 1 <" rst $end
$comment statein is not handled $end
$var reg 64 =" alpha[63:0] $end
$comment stateout is not handled $end
$upscope $end
$upscope $end
$scope module genstages(34) $end
$scope module cstage $end
$var reg 1 >" clk $end
$var reg 1 ?" rst $end
$comment statein is not handled $end
$var reg 64 @" alpha[63:0] $end
$comment stateout is not handled $end
$upscope $end
$upscope $end
$scope module genstages(35) $end
$scope module cstage $end
$var reg 1 A" clk $end
$var reg 1 B" rst $end
$comment statein is not handled $end
$var reg 64 C" alpha[63:0] $end
$comment stateout is not handled $end
$upscope $end
$upscope $end
$scope module genstages(36) $end
$scope module cstage $end
$var reg 1 D" clk $end
$var reg 1 E" rst $end
$comment statein is not handled $end
$var reg 64 F" alpha[63:0] $end
$comment stateout is not handled $end
$upscope $end
$upscope $end
$scope module genstages(37) $end
$scope module cstage $end
$var reg 1 G" clk $end
$var reg 1 H" rst $end
$comment statein is not handled $end
$var reg 64 I" alpha[63:0] $end
$comment stateout is not handled $end
$upscope $end
$upscope $end
$scope module genstages(38) $end
$scope module cstage $end
$var reg 1 J" clk $end
$var reg 1 K" rst $end
$comment statein is not handled $end
$var reg 64 L" alpha[63:0] $end
$comment stateout is not handled $end
$upscope $end
$upscope $end
$scope module genstages(39) $end
$scope module cstage $end
$var reg 1 M" clk $end
$var reg 1 N" rst $end
$comment statein is not handled $end
$var reg 64 O" alpha[63:0] $end
$comment stateout is not handled $end
$upscope $end
$upscope $end
$scope module genstages(40) $end
$scope module cstage $end
$var reg 1 P" clk $end
$var reg 1 Q" rst $end
$comment statein is not handled $end
$var reg 64 R" alpha[63:0] $end
$comment stateout is not handled $end
$upscope $end
$upscope $end
$scope module genstages(41) $end
$scope module cstage $end
$var reg 1 S" clk $end
$var reg 1 T" rst $end
$comment statein is not handled $end
$var reg 64 U" alpha[63:0] $end
$comment stateout is not handled $end
$upscope $end
$upscope $end
$scope module genstages(42) $end
$scope module cstage $end
$var reg 1 V" clk $end
$var reg 1 W" rst $end
$comment statein is not handled $end
$var reg 64 X" alpha[63:0] $end
$comment stateout is not handled $end
$upscope $end
$upscope $end
$scope module genstages(43) $end
$scope module cstage $end
$var reg 1 Y" clk $end
$var reg 1 Z" rst $end
$comment statein is not handled $end
$var reg 64 [" alpha[63:0] $end
$comment stateout is not handled $end
$upscope $end
$upscope $end
$scope module genstages(44) $end
$scope module cstage $end
$var reg 1 \" clk $end
$var reg 1 ]" rst $end
$comment statein is not handled $end
$var reg 64 ^" alpha[63:0] $end
$comment stateout is not handled $end
$upscope $end
$upscope $end
$scope module genstages(45) $end
$scope module cstage $end
$var reg 1 _" clk $end
$var reg 1 `" rst $end
$comment statein is not handled $end
$var reg 64 a" alpha[63:0] $end
$comment stateout is not handled $end
$upscope $end
$upscope $end
$scope module genstages(46) $end
$scope module cstage $end
$var reg 1 b" clk $end
$var reg 1 c" rst $end
$comment statein is not handled $end
$var reg 64 d" alpha[63:0] $end
$comment stateout is not handled $end
$upscope $end
$upscope $end
$scope module genstages(47) $end
$scope module cstage $end
$var reg 1 e" clk $end
$var reg 1 f" rst $end
$comment statein is not handled $end
$var reg 64 g" alpha[63:0] $end
$comment stateout is not handled $end
$upscope $end
$upscope $end
$upscope $end
$upscope $end
$upscope $end
$enddefinitions $end
#0
0!
1"
b0000000000000000000000000000000000000000000000000000000000000000 #
b0000000000000000000000000000000000000000000000000000000000000000 $
b0000000000000000000000000000000000000000000000000000000000000000 %
b00011010001010110011110001001101 &
0'
1(
b0000000000000000000000000000000000000000000000000000000000000000 )
b0000000000000000000000000000000000000000000000000000000000000000 *
b0000000000000000000000000000000000000000000000000000000000000000 +
b0000000000000000000000000000000000000000000000000000000000000000 ,
0-
0.
1/
b0000000000000000000000000000000000000000000000000000000000000000 0
b0000000000000000000000000000000000000000000000000000000000000000 1
02
03
14
05
16
b0000000000000000110010010000111111011010101000100010000101101001 7
08
19
b0000000000000000011101101011000110011100000101011000011011101101 :
0;
1<
b0000000000000000001111101011011011101011111100100101100100000010 =
0>
1?
b0000000000000000000111111101010110111010100110101010110000101111 @
0A
1B
b0000000000000000000011111111101010101101110110111001011001111111 C
0D
1E
b0000000000000000000001111111111101010101011011101110101001011110 F
0G
1H
b0000000000000000000000111111111111101010101010110111011101101110 I
0J
1K
b0000000000000000000000011111111111111101010101010101101110111100 L
0M
1N
b0000000000000000000000001111111111111111101010101010101011011110 O
0P
1Q
b0000000000000000000000000111111111111111111101010101010101010111 R
0S
1T
b0000000000000000000000000011111111111111111111101010101010101011 U
0V
1W
b0000000000000000000000000001111111111111111111111101010101010101 X
0Y
1Z
b0000000000000000000000000000111111111111111111111111101010101011 [
0\
1]
b0000000000000000000000000000011111111111111111111111111101010101 ^
0_
1`
b0000000000000000000000000000001111111111111111111111111111101011 a
0b
1c
b0000000000000000000000000000000111111111111111111111111111111101 d
0e
1f
b0000000000000000000000000000000100000000000000000000000000000000 g
0h
1i
b0000000000000000000000000000000010000000000000000000000000000000 j
0k
1l
b0000000000000000000000000000000001000000000000000000000000000000 m
0n
1o
b0000000000000000000000000000000000100000000000000000000000000000 p
0q
1r
b0000000000000000000000000000000000010000000000000000000000000000 s
0t
1u
b0000000000000000000000000000000000001000000000000000000000000000 v
0w
1x
b0000000000000000000000000000000000000100000000000000000000000000 y
0z
1{
b0000000000000000000000000000000000000010000000000000000000000000 |
0}
1!"
b0000000000000000000000000000000000000001000000000000000000000000 ""
0#"
1$"
b0000000000000000000000000000000000000000100000000000000000000000 %"
0&"
1'"
b0000000000000000000000000000000000000000010000000000000000000000 ("
0)"
1*"
b0000000000000000000000000000000000000000001000000000000000000000 +"
0,"
1-"
b0000000000000000000000000000000000000000000100000000000000000000 ."
0/"
10"
b0000000000000000000000000000000000000000000010000000000000000000 1"
02"
13"
b0000000000000000000000000000000000000000000001000000000000000000 4"
05"
16"
b0000000000000000000000000000000000000000000000100000000000000000 7"
08"
19"
b0000000000000000000000000000000000000000000000010000000000000000 :"
0;"
1<"
b0000000000000000000000000000000000000000000000001000000000000000 ="
0>"
1?"
b0000000000000000000000000000000000000000000000000100000000000000 @"
0A"
1B"
b0000000000000000000000000000000000000000000000000010000000000000 C"
0D"
1E"
b0000000000000000000000000000000000000000000000000001000000000000 F"
0G"
1H"
b0000000000000000000000000000000000000000000000000000100000000000 I"
0J"
1K"
b0000000000000000000000000000000000000000000000000000010000000000 L"
0M"
1N"
b0000000000000000000000000000000000000000000000000000001000000000 O"
0P"
1Q"
b0000000000000000000000000000000000000000000000000000000100000000 R"
0S"
1T"
b0000000000000000000000000000000000000000000000000000000010000000 U"
0V"
1W"
b0000000000000000000000000000000000000000000000000000000001000000 X"
0Y"
1Z"
b0000000000000000000000000000000000000000000000000000000000100000 ["
0\"
1]"
b0000000000000000000000000000000000000000000000000000000000010000 ^"
0_"
1`"
b0000000000000000000000000000000000000000000000000000000000001000 a"
0b"
1c"
b0000000000000000000000000000000000000000000000000000000000000100 d"
0e"
1f"
b0000000000000000000000000000000000000000000000000000000000000010 g"
#5000000
1!
0"
1'
0(
1.
0/
13
04
15
06
18
09
1;
0<
1>
0?
1A
0B
1D
0E
1G
0H
1J
0K
1M
0N
1P
0Q
1S
0T
1V
0W
1Y
0Z
1\
0]
1_
0`
1b
0c
1e
0f
1h
0i
1k
0l
1n
0o
1q
0r
1t
0u
1w
0x
1z
0{
1}
0!"
1#"
0$"
1&"
0'"
1)"
0*"
1,"
0-"
1/"
00"
12"
03"
15"
06"
18"
09"
1;"
0<"
1>"
0?"
1A"
0B"
1D"
0E"
1G"
0H"
1J"
0K"
1M"
0N"
1P"
0Q"
1S"
0T"
1V"
0W"
1Y"
0Z"
1\"
0]"
1_"
0`"
1b"
0c"
1e"
0f"
#10000000
0!
0'
0.
03
05
08
0;
0>
0A
0D
0G
0J
0M
0P
0S
0V
0Y
0\
0_
0b
0e
0h
0k
0n
0q
0t
0w
0z
0}
0#"
0&"
0)"
0,"
0/"
02"
05"
08"
0;"
0>"
0A"
0D"
0G"
0J"
0M"
0P"
0S"
0V"
0Y"
0\"
0_"
0b"
0e"
#15000000
1!
b0000000000000000100001100000101010010001110000010110101110011011 #
1'
b0000000000000000100001100000101010010001110000010110101110011011 )
1.
b0000000000000000100001100000101010010001110000010110101110011011 0
13
15
18
1;
1>
1A
1D
1G
1J
1M
1P
1S
1V
1Y
1\
1_
1b
1e
1h
1k
1n
1q
1t
1w
1z
1}
1#"
1&"
1)"
1,"
1/"
12"
15"
18"
1;"
1>"
1A"
1D"
1G"
1J"
1M"
1P"
1S"
1V"
1Y"
1\"
1_"
1b"
1e"
#20000000
0!
0'
0.
03
05
08
0;
0>
0A
0D
0G
0J
0M
0P
0S
0V
0Y
0\
0_
0b
0e
0h
0k
0n
0q
0t
0w
0z
0}
0#"
0&"
0)"
0,"
0/"
02"
05"
08"
0;"
0>"
0A"
0D"
0G"
0J"
0M"
0P"
0S"
0V"
0Y"
0\"
0_"
0b"
0e"
#25000000
1!
b0000000000000000110010010000111111011010101000100010000101101001 #
1'
b0000000000000000110010010000111111011010101000100010000101101001 )
b0000000000000000100001100000101010010001110000010110101110011011 ,
1.
b0000000000000000110010010000111111011010101000100010000101101001 0
b0000000000000000100001100000101010010001110000010110101110011011 1
13
15
18
1;
1>
1A
1D
1G
1J
1M
1P
1S
1V
1Y
1\
1_
1b
1e
1h
1k
1n
1q
1t
1w
1z
1}
1#"
1&"
1)"
1,"
1/"
12"
15"
18"
1;"
1>"
1A"
1D"
1G"
1J"
1M"
1P"
1S"
1V"
1Y"
1\"
1_"
1b"
1e"
#30000000
0!
0'
0.
03
05
08
0;
0>
0A
0D
0G
0J
0M
0P
0S
0V
0Y
0\
0_
0b
0e
0h
0k
0n
0q
0t
0w
0z
0}
0#"
0&"
0)"
0,"
0/"
02"
05"
08"
0;"
0>"
0A"
0D"
0G"
0J"
0M"
0P"
0S"
0V"
0Y"
0\"
0_"
0b"
0e"
#35000000
1!
b0000000000000001000011000001010100100011100000101101011100110110 #
1'
b0000000000000001000011000001010100100011100000101101011100110110 )
b0000000000000000110010010000111111011010101000100010000101101001 ,
1.
b0000000000000001000011000001010100100011100000101101011100110110 0
b0000000000000000110010010000111111011010101000100010000101101001 1
13
15
18
1;
1>
1A
1D
1G
1J
1M
1P
1S
1V
1Y
1\
1_
1b
1e
1h
1k
1n
1q
1t
1w
1z
1}
1#"
1&"
1)"
1,"
1/"
12"
15"
18"
1;"
1>"
1A"
1D"
1G"
1J"
1M"
1P"
1S"
1V"
1Y"
1\"
1_"
1b"
1e"
#40000000
0!
0'
0.
03
05
08
0;
0>
0A
0D
0G
0J
0M
0P
0S
0V
0Y
0\
0_
0b
0e
0h
0k
0n
0q
0t
0w
0z
0}
0#"
0&"
0)"
0,"
0/"
02"
05"
08"
0;"
0>"
0A"
0D"
0G"
0J"
0M"
0P"
0S"
0V"
0Y"
0\"
0_"
0b"
0e"
#45000000
1!
b0000000000000001100100100001111110110101010001000100001011010010 #
1'
b0000000000000001100100100001111110110101010001000100001011010010 )
b0000000000000001000011000001010100100011100000101101011100110110 ,
1.
b0000000000000001100100100001111110110101010001000100001011010010 0
b0000000000000001000011000001010100100011100000101101011100110110 1
13
15
18
1;
1>
1A
1D
1G
1J
1M
1P
1S
1V
1Y
1\
1_
1b
1e
1h
1k
1n
1q
1t
1w
1z
1}
1#"
1&"
1)"
1,"
1/"
12"
15"
18"
1;"
1>"
1A"
1D"
1G"
1J"
1M"
1P"
1S"
1V"
1Y"
1\"
1_"
1b"
1e"
#50000000
0!
0'
0.
03
05
08
0;
0>
0A
0D
0G
0J
0M
0P
0S
0V
0Y
0\
0_
0b
0e
0h
0k
0n
0q
0t
0w
0z
0}
0#"
0&"
0)"
0,"
0/"
02"
05"
08"
0;"
0>"
0A"
0D"
0G"
0J"
0M"
0P"
0S"
0V"
0Y"
0\"
0_"
0b"
0e"
#55000000
1!
b0000000000000010000110000010101001000111000001011010111001101101 #
1'
b0000000000000010000110000010101001000111000001011010111001101101 )
b0000000000000001100100100001111110110101010001000100001011010010 ,
1.
b0000000000000010000110000010101001000111000001011010111001101101 0
b0000000000000001100100100001111110110101010001000100001011010010 1
13
15
18
1;
1>
1A
1D
1G
1J
1M
1P
1S
1V
1Y
1\
1_
1b
1e
1h
1k
1n
1q
1t
1w
1z
1}
1#"
1&"
1)"
1,"
1/"
12"
15"
18"
1;"
1>"
1A"
1D"
1G"
1J"
1M"
1P"
1S"
1V"
1Y"
1\"
1_"
1b"
1e"
#60000000
0!
0'
0.
03
05
08
0;
0>
0A
0D
0G
0J
0M
0P
0S
0V
0Y
0\
0_
0b
0e
0h
0k
0n
0q
0t
0w
0z
0}
0#"
0&"
0)"
0,"
0/"
02"
05"
08"
0;"
0>"
0A"
0D"
0G"
0J"
0M"
0P"
0S"
0V"
0Y"
0\"
0_"
0b"
0e"
#65000000
1!
b0000000000000010100111100011010011011000110001110001101000001000 #
1'
b0000000000000010100111100011010011011000110001110001101000001000 )
b0000000000000010000110000010101001000111000001011010111001101101 ,
1.
b0000000000000010100111100011010011011000110001110001101000001000 0
b0000000000000010000110000010101001000111000001011010111001101101 1
13
15
18
1;
1>
1A
1D
1G
1J
1M
1P
1S
1V
1Y
1\
1_
1b
1e
1h
1k
1n
1q
1t
1w
1z
1}
1#"
1&"
1)"
1,"
1/"
12"
15"
18"
1;"
1>"
1A"
1D"
1G"
1J"
1M"
1P"
1S"
1V"
1Y"
1\"
1_"
1b"
1e"
#70000000
0!
0'
0.
03
05
08
0;
0>
0A
0D
0G
0J
0M
0P
0S
0V
0Y
0\
0_
0b
0e
0h
0k
0n
0q
0t
0w
0z
0}
0#"
0&"
0)"
0,"
0/"
02"
05"
08"
0;"
0>"
0A"
0D"
0G"
0J"
0M"
0P"
0S"
0V"
0Y"
0\"
0_"
0b"
0e"
